dotloop/__init__.py
dotloop/account.py
dotloop/activity.py
dotloop/auth.py
dotloop/base_client.py
dotloop/client.py
dotloop/contact.py
dotloop/document.py
dotloop/enums.py
dotloop/exceptions.py
dotloop/folder.py
dotloop/loop.py
dotloop/loop_detail.py
dotloop/loop_it.py
dotloop/participant.py
dotloop/profile.py
dotloop/py.typed
dotloop/task.py
dotloop/template.py
dotloop/webhook.py
dotloop-1.3.0.dist-info/licenses/LICENSE
dotloop-1.3.0.dist-info/METADATA
dotloop-1.3.0.dist-info/WHEEL
dotloop-1.3.0.dist-info/top_level.txt
dotloop-1.3.0.dist-info/RECORD
